client/__init__.py
client/client.py
client/client_side/__init__.py
client/client_side/add_contact.py
client/client_side/database.py
client/client_side/del_contact.py
client/client_side/main_window.py
client/client_side/main_window_conv.py
client/client_side/start_dialog.py
client/client_side/transport.py
client/common/__init__.py
client/common/decos.py
client/common/descryptors.py
client/common/errors.py
client/common/metaclasses.py
client/common/utils.py
client/common/variables.py
client/logs/__init__.py
client/logs/config_client_log.py
client/logs/config_server_log.py
client/unit_tests/__init__.py
client/unit_tests/test_client.py
client/unit_tests/test_utils.py
py_mess_client_by_rufus-0.0.1.dist-info/METADATA
py_mess_client_by_rufus-0.0.1.dist-info/WHEEL
py_mess_client_by_rufus-0.0.1.dist-info/top_level.txt
py_mess_client_by_rufus-0.0.1.dist-info/RECORD
