Metadata-Version: 2.1
Name: py-mess-client-by-rufus
Version: 0.0.1
Summary: Mess Client
Home-page: UNKNOWN
Author: Anton
Author-email: 11@11.ru
License: UNKNOWN
Platform: UNKNOWN
Requires-Dist: PyQt5
Requires-Dist: sqlalchemy
Requires-Dist: pycryptodome
Requires-Dist: pycryptodomex
